Metadata-Version: 2.1
Name: airflow-mailgun-email
Version: 1.0.2
Summary: Email Backend for Airflow To send email via Mailgun API
Home-page: UNKNOWN
Author: Dinesh Sawant
Author-email: dineshsawant300@gmail.com
License: UNKNOWN
Platform: UNKNOWN
Classifier: Programming Language :: Python :: 3
Classifier: License :: OSI Approved :: MIT License
Classifier: Operating System :: OS Independent
Requires-Python: >=3.6
